pycom_annek/__init__.py
pycom_annek/cli.py
pycom_annek-1.2.1.dist-info/METADATA
pycom_annek-1.2.1.dist-info/WHEEL
pycom_annek-1.2.1.dist-info/entry_points.txt
pycom_annek-1.2.1.dist-info/RECORD
